pyfind.py
pyfindtool-0.14.dist-info/METADATA
pyfindtool-0.14.dist-info/WHEEL
pyfindtool-0.14.dist-info/top_level.txt
pyfindtool-0.14.dist-info/RECORD
