Metadata-Version: 2.1
Name: pyfindtool
Version: 0.14
Summary: tool to search a directory tree for files matching some criteria, in a way similar to GNU find
Author-email: maxpat78 <maxpat78@yahoo.it>
License: Public Domain
Project-URL: homepage, https://github.com/maxpat78/PyFind
Project-URL: repository, https://github.com/maxpat78/PyFind.git
Keywords: find,search,filesystem
Classifier: Programming Language :: Python :: 3
Classifier: Intended Audience :: Developers
Classifier: Intended Audience :: System Administrators
Classifier: License :: Public Domain
Classifier: Operating System :: Microsoft :: Windows
Classifier: Operating System :: POSIX :: Linux
Classifier: Topic :: System :: Filesystems
Requires-Python: >=3.0
